dpypx/__init__.py
dpypx/autodraw.py
dpypx/canvas.py
dpypx/client.py
dpypx/colours.py
dpypx/errors.py
dpypx/ratelimits.py
dpypx-0.7.6.dist-info/LICENSE.txt
dpypx-0.7.6.dist-info/METADATA
dpypx-0.7.6.dist-info/WHEEL
dpypx-0.7.6.dist-info/top_level.txt
dpypx-0.7.6.dist-info/RECORD
