Metadata-Version: 2.1
Name: dpypx
Version: 0.7.6
Summary: A wrapper for the Discord Python Pixels API.
Home-page: https://github.com/artemis21/dpypx
Author: Artemis
Author-email: artemis@artemisdev.xyz
License: UNKNOWN
Platform: UNKNOWN
Classifier: Programming Language :: Python :: 3
Classifier: License :: OSI Approved :: MIT License
Classifier: Operating System :: OS Independent
Requires-Python: >=3.7
License-File: LICENSE.txt
Requires-Dist: aiohttp
Requires-Dist: pillow
